automata_tools/Automata.py
automata_tools/BuildAutomata.py
automata_tools/DFAtoMinimizedDFA.py
automata_tools/NFAtoDFA.py
automata_tools/WFA.py
automata_tools/__init__.py
automata_tools/constants.py
automata_tools/utils.py
automata_tools-2.0.1.dist-info/LICENSE
automata_tools-2.0.1.dist-info/METADATA
automata_tools-2.0.1.dist-info/WHEEL
automata_tools-2.0.1.dist-info/top_level.txt
automata_tools-2.0.1.dist-info/RECORD
