Metadata-Version: 2.1
Name: automata-tools
Version: 2.0.1
Summary: Tools to build automata from your custom rule
Home-page: https://github.com/linonetwo/automata-tools
Author: LinOnetwo
Author-email: linonetwo012@gmail.com
License: UNKNOWN
Project-URL: Bug Reports, https://github.com/linonetwo/automata-tools/issues
Project-URL: Source, https://github.com/linonetwo/automata-tools/
Keywords: regex automata nlp regular expression state machine NFA DFA
Platform: UNKNOWN
Classifier: Development Status :: 3 - Alpha
Classifier: Intended Audience :: Developers
Classifier: Intended Audience :: Information Technology
Classifier: Topic :: Text Processing
Classifier: Topic :: Text Processing :: Filters
Classifier: Topic :: Text Processing :: Linguistic
Classifier: License :: OSI Approved :: MIT License
Classifier: Operating System :: OS Independent
Classifier: Programming Language :: Python :: 3.6
Classifier: Programming Language :: Python :: 3.7
Classifier: Programming Language :: Python :: 3.8
Classifier: Typing :: Typed
Requires-Python: >=3.6
Provides-Extra: dev
Provides-Extra: test
